vespasian/__init__.py
vespasian/cli.py
vespasian/util.py
vespasian/vespasian.py
vespasian-0.2.0.dist-info/LICENSE
vespasian-0.2.0.dist-info/METADATA
vespasian-0.2.0.dist-info/WHEEL
vespasian-0.2.0.dist-info/entry_points.txt
vespasian-0.2.0.dist-info/top_level.txt
vespasian-0.2.0.dist-info/zip-safe
vespasian-0.2.0.dist-info/RECORD
